DQN/DQN.py
DQN/__init__.py
DQN/five_rooms.py
huangzilongDQN-1.0.1.dist-info/METADATA
huangzilongDQN-1.0.1.dist-info/WHEEL
huangzilongDQN-1.0.1.dist-info/top_level.txt
huangzilongDQN-1.0.1.dist-info/RECORD
