Metadata-Version: 2.1
Name: huangzilongDQN
Version: 1.0.1
Summary: A print test for PyPI
Home-page: UNKNOWN
Author: huangzilong
Author-email: 371007354@qq.com
License: MIT
Keywords: ga nn
Platform: UNKNOWN
Requires-Python: >=3
